ifcclient/InfiniteFlightConnect.py
ifcclient/__init__.py
ifcclient/__version__.py
ifcclient/example.py
ifcclient/utils.py
ifcclient-0.0.6.dist-info/LICENSE
ifcclient-0.0.6.dist-info/METADATA
ifcclient-0.0.6.dist-info/WHEEL
ifcclient-0.0.6.dist-info/top_level.txt
ifcclient-0.0.6.dist-info/RECORD
