Metadata-Version: 2.1
Name: ifcclient
Version: 0.0.6
Summary: Python client for Infinite Flight Connect API v1/2
Home-page: https://github.com/rollingonroad/InfiniteFlightConnect
Author: David Wu
Author-email: toffino@aliyun.com
License: Apache 2.0
Platform: UNKNOWN
Classifier: License :: OSI Approved :: Apache Software License
Classifier: Natural Language :: English
Classifier: Operating System :: OS Independent
Classifier: Programming Language :: Python
License-File: LICENSE
